nanopy_dual/__init__.py
nanopy_dual/hashcat.py
nanopy_dual/learning_ai.py
nanopy_dual/loop_cracker.py
nanopy_dual/main.py
nanopy_dual/pattern_generator.py
nanopy_dual/server.py
nanopy_dual/storage.py
nanopy_dual/static/app.js
nanopy_dual/static/index.html
nanopy_dual/static/styles.css
nanopy_dual-1.0.42.dist-info/METADATA
nanopy_dual-1.0.42.dist-info/WHEEL
nanopy_dual-1.0.42.dist-info/entry_points.txt
nanopy_dual-1.0.42.dist-info/top_level.txt
nanopy_dual-1.0.42.dist-info/RECORD
