Metadata-Version: 2.4
Name: nanopy-dual
Version: 1.0.42
Summary: Hashcat GPU Cracker with Learning AI Loop
Home-page: https://github.com/Complexity-ML/hashcat-dual
Author: NanoPy Team
Author-email: dev@nanopy.chain
Keywords: hashcat gpu cracking password learning ai leveldb
Classifier: Development Status :: 4 - Beta
Classifier: Intended Audience :: Developers
Classifier: License :: OSI Approved :: MIT License
Classifier: Programming Language :: Python :: 3
Classifier: Programming Language :: Python :: 3.10
Classifier: Programming Language :: Python :: 3.11
Classifier: Programming Language :: Python :: 3.12
Requires-Python: >=3.8
Requires-Dist: aiohttp>=3.8.0
Requires-Dist: click>=8.0.0
Requires-Dist: rich>=12.0.0
Requires-Dist: plyvel>=1.5.0
Requires-Dist: requests>=2.28.0
Dynamic: author
Dynamic: author-email
Dynamic: classifier
Dynamic: description
Dynamic: description-content-type
Dynamic: home-page
Dynamic: keywords
Dynamic: requires-dist
Dynamic: requires-python
Dynamic: summary
